dictabase/__init__.py
dictabase/base_table.py
dictabase/database_worker.py
dictabase/helpers.py
Dictabase-4.0.16.dist-info/METADATA
Dictabase-4.0.16.dist-info/WHEEL
Dictabase-4.0.16.dist-info/top_level.txt
Dictabase-4.0.16.dist-info/RECORD
