Metadata-Version: 2.1
Name: Dictabase
Version: 4.0.16
Summary: A database interface that mimics a python dictionary.
Home-page: https://github.com/GrantGMiller/dictabase
Author: Grant miller
Author-email: grant@grant-miller.com
License: PSF
Project-URL: Source Code, https://github.com/GrantGMiller/dictabase
Keywords: dictionary database dictabase grant miller sqlalchemy flask sqlite dataset
Platform: UNKNOWN
Requires-Dist: dataset
